daybit-0.0.2.dist-info/DESCRIPTION.rst
daybit-0.0.2.dist-info/METADATA
daybit-0.0.2.dist-info/RECORD
daybit-0.0.2.dist-info/WHEEL
daybit-0.0.2.dist-info/metadata.json
daybit-0.0.2.dist-info/top_level.txt
pydaybit/__init__.py
pydaybit/daybit.py
pydaybit/daybit_channels.py
pydaybit/exceptions.py
pydaybit/ratelimit.py
pydaybit/utility.py
