Metadata-Version: 2.0
Name: daybit
Version: 0.0.2
Summary: an API wrapper for Daybit-exchange
Home-page: https://github.com/daybit-exchange/pydaybit
Author: Daybit Developers
License: UNKNOWN
Platform: UNKNOWN
Classifier: Programming Language :: Python :: 3
Classifier: License :: OSI Approved :: Apache Software License
Requires-Dist: async-timeout
Requires-Dist: dateparser
Requires-Dist: furl
Requires-Dist: numpy
Requires-Dist: pandas
Requires-Dist: pytz
Requires-Dist: tabulate
Requires-Dist: websockets
